asyncpraw/__init__.py
asyncpraw/config.py
asyncpraw/const.py
asyncpraw/endpoints.py
asyncpraw/exceptions.py
asyncpraw/objector.py
asyncpraw/praw.ini
asyncpraw/reddit.py
asyncpraw/images/PRAW logo.png
asyncpraw/models/__init__.py
asyncpraw/models/auth.py
asyncpraw/models/base.py
asyncpraw/models/comment_forest.py
asyncpraw/models/front.py
asyncpraw/models/helpers.py
asyncpraw/models/inbox.py
asyncpraw/models/mod_action.py
asyncpraw/models/mod_note.py
asyncpraw/models/mod_notes.py
asyncpraw/models/preferences.py
asyncpraw/models/redditors.py
asyncpraw/models/stylesheet.py
asyncpraw/models/subreddits.py
asyncpraw/models/trophy.py
asyncpraw/models/user.py
asyncpraw/models/util.py
asyncpraw/models/list/__init__.py
asyncpraw/models/list/base.py
asyncpraw/models/list/draft.py
asyncpraw/models/list/moderated.py
asyncpraw/models/list/redditor.py
asyncpraw/models/list/trophy.py
asyncpraw/models/listing/__init__.py
asyncpraw/models/listing/domain.py
asyncpraw/models/listing/generator.py
asyncpraw/models/listing/listing.py
asyncpraw/models/listing/mixins/__init__.py
asyncpraw/models/listing/mixins/base.py
asyncpraw/models/listing/mixins/gilded.py
asyncpraw/models/listing/mixins/redditor.py
asyncpraw/models/listing/mixins/rising.py
asyncpraw/models/listing/mixins/submission.py
asyncpraw/models/listing/mixins/subreddit.py
asyncpraw/models/reddit/__init__.py
asyncpraw/models/reddit/base.py
asyncpraw/models/reddit/collections.py
asyncpraw/models/reddit/comment.py
asyncpraw/models/reddit/draft.py
asyncpraw/models/reddit/emoji.py
asyncpraw/models/reddit/inline_media.py
asyncpraw/models/reddit/live.py
asyncpraw/models/reddit/message.py
asyncpraw/models/reddit/modmail.py
asyncpraw/models/reddit/more.py
asyncpraw/models/reddit/multi.py
asyncpraw/models/reddit/poll.py
asyncpraw/models/reddit/redditor.py
asyncpraw/models/reddit/removal_reasons.py
asyncpraw/models/reddit/rules.py
asyncpraw/models/reddit/submission.py
asyncpraw/models/reddit/subreddit.py
asyncpraw-7.7.1.dist-info/AUTHORS.rst
asyncpraw-7.7.1.dist-info/LICENSE.txt
asyncpraw-7.7.1.dist-info/METADATA
asyncpraw-7.7.1.dist-info/WHEEL
asyncpraw-7.7.1.dist-info/top_level.txt
asyncpraw-7.7.1.dist-info/RECORD
