Metadata-Version: 2.1
Name: asyncpraw
Version: 7.7.1
Summary: Async PRAW, an abbreviation for "Asynchronous Python Reddit API Wrapper", is a python package that allows for simple access to Reddit's API.
Author: Joel Payne
Author-email: lilspazjoekp@gmail.com
License: Simplified BSD License
Project-URL: Change Log, https://asyncpraw.readthedocs.io/en/latest/package_info/change_log.html
Project-URL: Documentation, https://asyncpraw.readthedocs.io/
Project-URL: Issue Tracker, https://github.com/praw-dev/asyncpraw/issues
Project-URL: Source Code, https://github.com/praw-dev/asyncpraw
Keywords: reddit api wrapper asyncpraw praw async asynchronous
Classifier: Development Status :: 5 - Production/Stable
Classifier: Environment :: Console
Classifier: Intended Audience :: Developers
Classifier: License :: OSI Approved :: BSD License
Classifier: Natural Language :: English
Classifier: Operating System :: OS Independent
Classifier: Programming Language :: Python
Classifier: Programming Language :: Python :: 3
Classifier: Programming Language :: Python :: 3.7
Classifier: Programming Language :: Python :: 3.8
Classifier: Programming Language :: Python :: 3.9
Classifier: Programming Language :: Python :: 3.10
Classifier: Programming Language :: Python :: 3.11
Classifier: Topic :: Utilities
Requires-Python: >=3.7
Provides-Extra: ci
Provides-Extra: dev
Provides-Extra: lint
Provides-Extra: readthedocs
Provides-Extra: test
License-File: LICENSE.txt
License-File: AUTHORS.rst
